lhotse/__init__.py
lhotse/array.py
lhotse/caching.py
lhotse/custom.py
lhotse/hf.py
lhotse/kaldi.py
lhotse/lazy.py
lhotse/manipulation.py
lhotse/parallel.py
lhotse/qa.py
lhotse/serialization.py
lhotse/supervision.py
lhotse/utils.py
lhotse/version.py
lhotse/workarounds.py
lhotse/audio/__init__.py
lhotse/audio/backend.py
lhotse/audio/mixer.py
lhotse/audio/recording.py
lhotse/audio/recording_set.py
lhotse/audio/source.py
lhotse/audio/utils.py
lhotse/augmentation/__init__.py
lhotse/augmentation/clipping.py
lhotse/augmentation/common.py
lhotse/augmentation/loudness.py
lhotse/augmentation/resample.py
lhotse/augmentation/rir.py
lhotse/augmentation/torchaudio.py
lhotse/augmentation/transform.py
lhotse/augmentation/utils.py
lhotse/augmentation/wpe.py
lhotse/bin/__init__.py
lhotse/bin/lhotse.py
lhotse/bin/modes/__init__.py
lhotse/bin/modes/cli_base.py
lhotse/bin/modes/cut.py
lhotse/bin/modes/features.py
lhotse/bin/modes/install_tools.py
lhotse/bin/modes/kaldi.py
lhotse/bin/modes/manipulation.py
lhotse/bin/modes/shar.py
lhotse/bin/modes/supervision.py
lhotse/bin/modes/utils.py
lhotse/bin/modes/validate.py
lhotse/bin/modes/workflows.py
lhotse/bin/modes/recipes/__init__.py
lhotse/bin/modes/recipes/adept.py
lhotse/bin/modes/recipes/aidatatang_200zh.py
lhotse/bin/modes/recipes/aishell.py
lhotse/bin/modes/recipes/aishell2.py
lhotse/bin/modes/recipes/aishell3.py
lhotse/bin/modes/recipes/aishell4.py
lhotse/bin/modes/recipes/ali_meeting.py
lhotse/bin/modes/recipes/ami.py
lhotse/bin/modes/recipes/aspire.py
lhotse/bin/modes/recipes/atcosim.py
lhotse/bin/modes/recipes/audio_mnist.py
lhotse/bin/modes/recipes/babel.py
lhotse/bin/modes/recipes/baker_zh.py
lhotse/bin/modes/recipes/bengaliai_speech.py
lhotse/bin/modes/recipes/broadcast_news.py
lhotse/bin/modes/recipes/but_reverb_db.py
lhotse/bin/modes/recipes/bvcc.py
lhotse/bin/modes/recipes/callhome_egyptian.py
lhotse/bin/modes/recipes/callhome_english.py
lhotse/bin/modes/recipes/cdsd.py
lhotse/bin/modes/recipes/chime6.py
lhotse-1.31.1.dist-info/LICENSE
lhotse-1.31.1.dist-info/METADATA
lhotse-1.31.1.dist-info/NOTICE
lhotse-1.31.1.dist-info/WHEEL
lhotse-1.31.1.dist-info/entry_points.txt
lhotse-1.31.1.dist-info/top_level.txt
lhotse-1.31.1.dist-info/RECORD
