Metadata-Version: 2.1
Name: lhotse
Version: 1.31.1
Summary: Data preparation for speech processing models training.
Author: The Lhotse Development Team
Author-email: pzelasko@jhu.edu
License: Apache-2.0 License
Classifier: Development Status :: 5 - Production/Stable
Classifier: Programming Language :: Python :: 3.8
Classifier: Programming Language :: Python :: 3.9
Classifier: Programming Language :: Python :: 3.10
Classifier: Programming Language :: Python :: 3.11
Classifier: Programming Language :: Python :: 3.12
Classifier: Intended Audience :: Science/Research
Classifier: Operating System :: POSIX :: Linux
Classifier: Operating System :: MacOS :: MacOS X
Classifier: Operating System :: Microsoft :: Windows
Classifier: License :: OSI Approved :: Apache Software License
Classifier: Topic :: Multimedia :: Sound/Audio :: Speech
Classifier: Topic :: Scientific/Engineering :: Artificial Intelligence
Classifier: Topic :: Software Development :: Libraries :: Python Modules
Classifier: Typing :: Typed
Requires-Python: >=3.8.0
License-File: LICENSE
License-File: NOTICE
Requires-Dist: audioread >=2.1.9
Requires-Dist: SoundFile >=0.10
Requires-Dist: click >=7.1.1
Requires-Dist: cytoolz >=0.10.1
Requires-Dist: intervaltree >=3.1.0
Requires-Dist: numpy >=1.18.1
Requires-Dist: packaging
Requires-Dist: pyyaml >=5.3.1
Requires-Dist: tabulate >=0.8.1
Requires-Dist: torch
Requires-Dist: tqdm
Requires-Dist: lilcom >=1.1.0
Provides-Extra: all
Requires-Dist: black ==22.3.0 ; extra == 'all'
Requires-Dist: coverage ==6.5.0 ; extra == 'all'
Requires-Dist: dill ; extra == 'all'
Requires-Dist: flake8 ==5.0.4 ; extra == 'all'
Requires-Dist: hypothesis ==6.56.0 ; extra == 'all'
Requires-Dist: isort ==5.10.1 ; extra == 'all'
Requires-Dist: jupyterlab ; extra == 'all'
Requires-Dist: matplotlib ; extra == 'all'
Requires-Dist: numpy >=1.18.1 ; extra == 'all'
Requires-Dist: orjson >=3.6.6 ; extra == 'all'
Requires-Dist: pillow ; extra == 'all'
Requires-Dist: pre-commit <=2.19.0,>=2.17.0 ; extra == 'all'
Requires-Dist: pytest-cov ==4.0.0 ; extra == 'all'
Requires-Dist: pytest-forked ==1.4.0 ; extra == 'all'
Requires-Dist: pytest-xdist ==2.5.0 ; extra == 'all'
Requires-Dist: pytest ==7.1.3 ; extra == 'all'
Requires-Dist: scipy ; extra == 'all'
Requires-Dist: sphinx-autodoc-typehints ==2.0.0 ; extra == 'all'
Requires-Dist: sphinx-click ==5.1.0 ; extra == 'all'
Requires-Dist: sphinx ==7.1.2 ; extra == 'all'
Requires-Dist: sphinx-rtd-theme ==2.0.0 ; extra == 'all'
Requires-Dist: webdataset ==0.2.5 ; extra == 'all'
Provides-Extra: dev
Requires-Dist: black ==22.3.0 ; extra == 'dev'
Requires-Dist: coverage ==6.5.0 ; extra == 'dev'
Requires-Dist: dill ; extra == 'dev'
Requires-Dist: flake8 ==5.0.4 ; extra == 'dev'
Requires-Dist: hypothesis ==6.56.0 ; extra == 'dev'
Requires-Dist: isort ==5.10.1 ; extra == 'dev'
Requires-Dist: jupyterlab ; extra == 'dev'
Requires-Dist: matplotlib ; extra == 'dev'
Requires-Dist: numpy >=1.18.1 ; extra == 'dev'
Requires-Dist: orjson >=3.6.6 ; extra == 'dev'
Requires-Dist: pillow ; extra == 'dev'
Requires-Dist: pre-commit <=2.19.0,>=2.17.0 ; extra == 'dev'
Requires-Dist: pytest-cov ==4.0.0 ; extra == 'dev'
Requires-Dist: pytest-forked ==1.4.0 ; extra == 'dev'
Requires-Dist: pytest-xdist ==2.5.0 ; extra == 'dev'
Requires-Dist: pytest ==7.1.3 ; extra == 'dev'
Requires-Dist: scipy ; extra == 'dev'
Requires-Dist: sphinx-autodoc-typehints ==2.0.0 ; extra == 'dev'
Requires-Dist: sphinx-click ==5.1.0 ; extra == 'dev'
Requires-Dist: sphinx ==7.1.2 ; extra == 'dev'
Requires-Dist: sphinx-rtd-theme ==2.0.0 ; extra == 'dev'
Requires-Dist: webdataset ==0.2.5 ; extra == 'dev'
Provides-Extra: dill
Requires-Dist: dill ; extra == 'dill'
Provides-Extra: docs
Requires-Dist: numpy >=1.18.1 ; extra == 'docs'
Requires-Dist: sphinx-rtd-theme ==2.0.0 ; extra == 'docs'
Requires-Dist: sphinx ==7.1.2 ; extra == 'docs'
Requires-Dist: sphinx-click ==5.1.0 ; extra == 'docs'
Requires-Dist: sphinx-autodoc-typehints ==2.0.0 ; extra == 'docs'
Provides-Extra: h5py
Requires-Dist: h5py ; extra == 'h5py'
Provides-Extra: kaldi
Requires-Dist: kaldi-native-io ; extra == 'kaldi'
Requires-Dist: kaldifeat ; extra == 'kaldi'
Provides-Extra: orjson
Requires-Dist: orjson >=3.6.6 ; extra == 'orjson'
Provides-Extra: pillow
Requires-Dist: pillow ; extra == 'pillow'
Provides-Extra: tests
Requires-Dist: pytest ==7.1.3 ; extra == 'tests'
Requires-Dist: pytest-forked ==1.4.0 ; extra == 'tests'
Requires-Dist: pytest-xdist ==2.5.0 ; extra == 'tests'
Requires-Dist: pytest-cov ==4.0.0 ; extra == 'tests'
Requires-Dist: flake8 ==5.0.4 ; extra == 'tests'
Requires-Dist: coverage ==6.5.0 ; extra == 'tests'
Requires-Dist: hypothesis ==6.56.0 ; extra == 'tests'
Requires-Dist: black ==22.3.0 ; extra == 'tests'
Requires-Dist: isort ==5.10.1 ; extra == 'tests'
Requires-Dist: pre-commit <=2.19.0,>=2.17.0 ; extra == 'tests'
Provides-Extra: webdataset
Requires-Dist: webdataset ==0.2.5 ; extra == 'webdataset'
